jum/__init__.py
jum/cache.py
jum/profiler.py
jum-0.8.dist-info/DESCRIPTION.rst
jum-0.8.dist-info/METADATA
jum-0.8.dist-info/RECORD
jum-0.8.dist-info/WHEEL
jum-0.8.dist-info/metadata.json
jum-0.8.dist-info/top_level.txt
