Metadata-Version: 2.0
Name: jum
Version: 0.8
Summary: An alternative to Joblib's Memory to cache python function in-file
Home-page: https://github.com/phizaz/jum
Author: Konpat Preechakul
Author-email: the.akita.ta@gmail.com
License: UNKNOWN
Keywords: cache,in-file
Platform: UNKNOWN
Requires-Dist: dill
Requires-Dist: xxhash
